pcreporter/__init__.py
pcreporter/__meta__.py
pcreporter/pcreporter.py
pcreporter/state.py
pcreporter/cli/__init__.py
pcreporter/cli/cmds.py
pcreporter/cli/main.py
pcreporter/cli/sendmsg.py
pcreporter/fn/__init__.py
pcreporter/fn/lock_screen.py
pcreporter/fn/shutdown.py
pcreporter/fn/tailscale.py
pcreporter/info/__init__.py
pcreporter/info/overview.py
pcreporter/info/programs.py
pcreporter/info/temp.py
pcreporter/info/usb.py
pcreporter/monitor/__init__.py
pcreporter/monitor/usb.py
pcreporter-20241004.dist-info/METADATA
pcreporter-20241004.dist-info/WHEEL
pcreporter-20241004.dist-info/entry_points.txt
pcreporter-20241004.dist-info/licenses/LICENSE
pcreporter-20241004.dist-info/RECORD
