Metadata-Version: 2.3
Name: pcreporter
Version: 20241004
Summary: Telegram BOT as a personal computer reporting service.
Project-URL: Homepage, https://github.com/ayham-1/pcreporter
Author-email: ayham <me@ayham.xyz>
Maintainer-email: ayham <me@ayham.xyz>
License: Copyright (c) 2024, Ayham A.F.
License-File: LICENSE
Keywords: security
Requires-Python: >=3.8
Requires-Dist: psutil
Requires-Dist: python-telegram-bot==21.3
Requires-Dist: requests
Requires-Dist: uptime
Requires-Dist: usb-monitor
